time_check_server/__init__.py
time_check_server/time_check.py
time_check_server_get-0.0.1.dist-info/METADATA
time_check_server_get-0.0.1.dist-info/WHEEL
time_check_server_get-0.0.1.dist-info/top_level.txt
time_check_server_get-0.0.1.dist-info/RECORD
